doppler/__init__.py
doppler/classes.py
doppler/client.py
doppler_secrets-0.5.0.dist-info/WHEEL
doppler_secrets-0.5.0.dist-info/METADATA
doppler_secrets-0.5.0.dist-info/RECORD
