Metadata-Version: 2.1
Name: doppler-secrets
Version: 0.5.0
Summary: Dead simple Doppler client
Home-page: https://github.com/fedecalendino/doppler-secrets
License: MIT
Keywords: doppler,secrets
Author: Fede Calendino
Author-email: fede@calendino.com
Requires-Python: >=3.10,<4.0
Classifier: Intended Audience :: Developers
Classifier: License :: OSI Approved :: MIT License
Classifier: Programming Language :: Python :: 3
Classifier: Programming Language :: Python :: 3.10
Classifier: Programming Language :: Python :: 3.11
Classifier: Programming Language :: Python :: 3.10
Classifier: Programming Language :: Python :: 3.11
Classifier: Programming Language :: Python :: 3.12
Classifier: Programming Language :: Python :: 3.13
Requires-Dist: cachetools (>=6.2.1,<7.0.0)
Requires-Dist: poetry-core (>=2.2.1,<3.0.0)
Requires-Dist: pyjson5 (>=2.0.0,<3.0.0)
Requires-Dist: requests (>=2.32.5,<3.0.0)
Project-URL: Documentation, https://github.com/fedecalendino/doppler-secrets/blob/main/README.md
